moremath/__init__.py
moremath/algebra.py
moremath/arithmetic.py
moremath/geometry.py
moremath/statistics.py
moremath-0.2.2.dist-info/LICENSE
moremath-0.2.2.dist-info/METADATA
moremath-0.2.2.dist-info/WHEEL
moremath-0.2.2.dist-info/top_level.txt
moremath-0.2.2.dist-info/RECORD
