Metadata-Version: 2.1
Name: moremath
Version: 0.2.2
Summary: A Python package for advanced mathematical operations
Author-email: Ananyo Bhattacharya <ananyobhattacharya10@gmail.com>
Classifier: Programming Language :: Python :: 3
Classifier: License :: OSI Approved :: MIT License
Classifier: Operating System :: OS Independent
Requires-Python: >=3.9
License-File: LICENSE
